langchain_kuzu-0.4.2.dist-info/METADATA
langchain_kuzu-0.4.2.dist-info/WHEEL
langchain_kuzu-0.4.2.dist-info/entry_points.txt
langchain_kuzu/__init__.py
langchain_kuzu/chains/graph_qa/__init__.py
langchain_kuzu/chains/graph_qa/kuzu.py
langchain_kuzu/chains/graph_qa/prompts.py
langchain_kuzu/graphs/graph_document.py
langchain_kuzu/graphs/graph_store.py
langchain_kuzu/graphs/kuzu_graph.py
langchain_kuzu-0.4.2.dist-info/RECORD
