Metadata-Version: 2.1
Name: langchain-kuzu
Version: 0.4.2
Summary: An integration package connecting Kùzu, an embedded graph database, and LangChain
Project-URL: Source Code, https://github.com/kuzudb/langchain-kuzu/tree/main/libs/kuzu
Project-URL: Release Notes, https://github.com/kuzudb/langchain-kuzu/releases
Project-URL: repository, https://github.com/kuzudb/langchain-kuzu
Requires-Python: <4.0,>=3.10
Requires-Dist: kuzu>=0.9.0
Requires-Dist: langchain>=0.3.22
Requires-Dist: langchain-core>=0.3.50
